pcf_decrypt/__init__.py
pcf_decrypt/__main__.py
pcf_decrypt-0.1.1.dist-info/DESCRIPTION.rst
pcf_decrypt-0.1.1.dist-info/entry_points.txt
pcf_decrypt-0.1.1.dist-info/METADATA
pcf_decrypt-0.1.1.dist-info/metadata.json
pcf_decrypt-0.1.1.dist-info/RECORD
pcf_decrypt-0.1.1.dist-info/top_level.txt
pcf_decrypt-0.1.1.dist-info/WHEEL
