Metadata-Version: 2.0
Name: pcf-decrypt
Version: 0.1.1
Summary: Decrypt encoded passwords in Cisco VPN pcf files.
Home-page: https://github.com/demosdemon/pcf_decrypt
Author: Joachim Brandon LeBlanc
Author-email: demosdemon@gmail.com
License: MIT
Keywords: pcf_decrypt
Platform: UNKNOWN
Classifier: Development Status :: 4 - Beta
Classifier: Intended Audience :: Developers
Classifier: Intended Audience :: System Administrators
Classifier: License :: OSI Approved :: MIT License
Classifier: Natural Language :: English
Classifier: Programming Language :: Python :: 2
Classifier: Programming Language :: Python :: 2.6
Classifier: Programming Language :: Python :: 2.7
Classifier: Programming Language :: Python :: 3
Classifier: Programming Language :: Python :: 3.3
Classifier: Programming Language :: Python :: 3.4
Requires-Dist: six (>=1.8.0,<2.0.0)
Requires-Dist: PyCrypto (>=2.6.1,<2.7.0)
